scalpel/__init__.py
scalpel/__version__.py
scalpel/any_io/__init__.py
scalpel/any_io/files.py
scalpel/any_io/mixins.py
scalpel/any_io/queue.py
scalpel/any_io/response.py
scalpel/any_io/robots.py
scalpel/any_io/selenium_spider.py
scalpel/any_io/static_spider.py
scalpel/core/__init__.py
scalpel/core/config.py
scalpel/core/message_pack.py
scalpel/core/response.py
scalpel/core/robots.py
scalpel/core/selenium.py
scalpel/core/spider.py
scalpel/green/__init__.py
scalpel/green/files.py
scalpel/green/mixins.py
scalpel/green/response.py
scalpel/green/robots.py
scalpel/green/selenium_spider.py
scalpel/green/static_spider.py
scalpel/green/utils/__init__.py
scalpel/green/utils/io.py
pyscalpel-0.2.0.dist-info/LICENSE
pyscalpel-0.2.0.dist-info/WHEEL
pyscalpel-0.2.0.dist-info/METADATA
pyscalpel-0.2.0.dist-info/RECORD
