Metadata-Version: 2.1
Name: pyscalpel
Version: 0.2.0
Summary: Your easy-to-use, fast and powerful web scraping library
Home-page: https://scalpel.readthedocs.io/en/stable
Keywords: trio,gevent,webscraping,crawler,asyncio
Author: lewoudar
Author-email: lewoudar@gmail.com
Requires-Python: >=3.7,<4.0
Classifier: Framework :: AsyncIO
Classifier: Framework :: Robot Framework :: Tool
Classifier: Framework :: Trio
Classifier: Intended Audience :: Developers
Classifier: Operating System :: OS Independent
Classifier: Programming Language :: Python :: 3
Classifier: Programming Language :: Python :: 3.10
Classifier: Programming Language :: Python :: 3.7
Classifier: Programming Language :: Python :: 3.8
Classifier: Programming Language :: Python :: 3.9
Classifier: Topic :: Utilities
Provides-Extra: full
Provides-Extra: gevent
Provides-Extra: trio
Requires-Dist: anyio (>=3.0.0,<4.0.0)
Requires-Dist: attrs (>=19.3.0,<20.0.0)
Requires-Dist: configuror (>=0.2.0,<0.3.0)
Requires-Dist: fake-useragent (>=0.1.11,<0.2.0)
Requires-Dist: gevent (>=20.9.0,<21.0.0); extra == "gevent" or extra == "full"
Requires-Dist: httpx (>=0.23.0,<0.24.0)
Requires-Dist: msgpack (>=1.0.0,<2.0.0)
Requires-Dist: parsel (>=1.5.2,<2.0.0)
Requires-Dist: rfc3986[idna] (>=1.4.0,<2.0.0)
Requires-Dist: selenium (>=3.141.0,<4.0.0)
Requires-Dist: trio (>=0.17.0,<0.18.0); extra == "trio" or extra == "full"
Project-URL: Bug Tracker, https://github.com/lewoudar/scalpel/issues
Project-URL: Documentation, https://scalpel.readthedocs.io/en/stable
Project-URL: Repository, https://github.com/lewoudar/scalpel
